userinputgetter/__init__.py
userinputgetter/date_input_getters.py
userinputgetter/numeric_input_getters.py
userinputgetter/string_input_getters.py
userinputgetter/user_input_getter.py
userinputgetter/utils/date_utils.py
userinputgetter-1.1.0.dist-info/METADATA
userinputgetter-1.1.0.dist-info/WHEEL
userinputgetter-1.1.0.dist-info/licenses/LICENSE.txt
userinputgetter-1.1.0.dist-info/RECORD
