Metadata-Version: 2.1
Name: userinputgetter
Version: 1.1.0
Summary: Provides an interface, and several implementations, of classes which continuously request command-line user input until a valid response has been attained, and parse the output as a desired type
Project-URL: Homepage, https://github.com/mcindoe/userinputgetter
Project-URL: Bug Tracker, https://github.com/mcindoe/userinputgetter/issues
Author-email: Conor McIndoe <conormcindoe1@gmail.com>
License-File: LICENSE.txt
Classifier: License :: OSI Approved :: MIT License
Classifier: Operating System :: OS Independent
Classifier: Programming Language :: Python :: 3
Requires-Python: >=3.7
